{
  "params": {
    "pop_size": 30,
    "max_iter": 120,
    "penalty_coef": 1000,
    "coop_gap": 5,
    "w_end": 0.4
  },
  "steps_list": [
    159,
    173,
    42,
    23,
    25,
    113,
    110,
    23,
    151,
    164,
    78,
    54,
    216,
    54,
    57,
    96,
    46,
    95,
    71,
    122,
    47,
    80,
    65,
    141,
    145,
    94,
    188,
    54,
    47,
    205,
    108,
    41,
    72,
    59,
    26,
    62,
    74,
    45,
    25,
    117,
    75,
    102,
    37,
    182,
    122,
    89,
    132,
    60,
    79,
    81
  ],
  "completed": 50
}