{
  "params": {
    "pop_size": 50,
    "max_iter": 40,
    "penalty_coef": 1000,
    "coop_gap": 5,
    "w_end": 0.4
  },
  "steps_list": [
    77,
    63,
    88,
    158,
    23,
    52,
    54,
    57,
    35,
    42,
    182,
    87,
    64,
    38,
    35,
    196,
    72,
    36,
    60,
    79,
    42,
    84,
    91,
    106,
    125,
    77,
    55,
    59,
    30,
    53,
    97,
    112,
    79,
    47,
    226,
    126,
    79,
    90,
    48,
    41,
    37,
    29,
    78,
    99,
    31,
    48,
    79,
    73,
    67,
    59
  ],
  "completed": 50
}